.gitignore
LICENSE
Makefile
README.md
list.json
pyproject.toml
setup.cfg
.github/pull_request_template.md
.github/ISSUE_TEMPLATE/bug_report.md
.github/ISSUE_TEMPLATE/feature_request.md
.github/workflows/coverage.yml
.github/workflows/publish_release.yml
.github/workflows/style.yml
src/orquestra/quantum/evolution.py
src/orquestra/quantum/py.typed
src/orquestra/quantum/typing.py
src/orquestra/quantum/utils.py
src/orquestra/quantum/wavefunction.py
src/orquestra/quantum/api/__init__.py
src/orquestra/quantum/api/circuit_runner.py
src/orquestra/quantum/api/circuit_runner_contracts.py
src/orquestra/quantum/api/estimation.py
src/orquestra/quantum/api/estimator_contract.py
src/orquestra/quantum/api/wavefunction_simulator.py
src/orquestra/quantum/api/wavefunction_simulator_contracts.py
src/orquestra/quantum/circuits/__init__.py
src/orquestra/quantum/circuits/_builtin_gates.py
src/orquestra/quantum/circuits/_circuit.py
src/orquestra/quantum/circuits/_gates.py
src/orquestra/quantum/circuits/_generators.py
src/orquestra/quantum/circuits/_itertools.py
src/orquestra/quantum/circuits/_matrices.py
src/orquestra/quantum/circuits/_operations.py
src/orquestra/quantum/circuits/_serde.py
src/orquestra/quantum/circuits/_testing.py
src/orquestra/quantum/circuits/_unitary_tools.py
src/orquestra/quantum/circuits/_wavefunction_operations.py
src/orquestra/quantum/circuits/layouts.py
src/orquestra/quantum/circuits/symbolic/__init__.py
src/orquestra/quantum/circuits/symbolic/_sorting.py
src/orquestra/quantum/circuits/symbolic/expressions.py
src/orquestra/quantum/circuits/symbolic/sympy_expressions.py
src/orquestra/quantum/circuits/symbolic/translations.py
src/orquestra/quantum/decompositions/__init__.py
src/orquestra/quantum/decompositions/_decomposition.py
src/orquestra/quantum/decompositions/_orquestra_decompositions.py
src/orquestra/quantum/distributions/BAS_dataset.py
src/orquestra/quantum/distributions/__init__.py
src/orquestra/quantum/distributions/_measurement_outcome_distribution.py
src/orquestra_quantum.egg-info/PKG-INFO
src/orquestra_quantum.egg-info/SOURCES.txt
src/orquestra_quantum.egg-info/dependency_links.txt
src/orquestra_quantum.egg-info/not-zip-safe
src/orquestra_quantum.egg-info/requires.txt
src/orquestra_quantum.egg-info/top_level.txt
