Metadata-Version: 2.1
Name: orquestra-quantum
Version: 0.12.0
Summary: "Orquestra's library with basic quantum operations"
Home-page: https://github.com/zapatacomputing/orquestra-quantum
Author: Zapata Computing Inc.
Author-email: info@zapatacomputing.com,
License: Apache Software License 2.0
Classifier: Programming Language :: Python :: 3
Classifier: Operating System :: OS Independent
Classifier: License :: OSI Approved :: Apache Software License
Classifier: Topic :: Scientific/Engineering
Requires-Python: !=3.9.7,>=3.9
License-File: LICENSE
Requires-Dist: numpy>=1.20
Requires-Dist: scipy>=1.4.1
Requires-Dist: sympy<=1.9,>=1.5
Requires-Dist: scikit-learn>=1.0
Requires-Dist: python-rapidjson>=1.5
Requires-Dist: h5py>=2.8
Provides-Extra: dev
Requires-Dist: orquestra-python-dev; extra == "dev"
